scannertext/__init__.py
scannertext/_scanner.py
scannertext/_scannerbase.py
scannertext/_stackentry.py
scannertext/_unicodeutils.py
scannertext-0.9.0.dist-info/licenses/LICENSE
scannertext-0.9.0.dist-info/METADATA
scannertext-0.9.0.dist-info/WHEEL
scannertext-0.9.0.dist-info/top_level.txt
scannertext-0.9.0.dist-info/RECORD
