Metadata-Version: 2.4
Name: scannertext
Version: 0.9.0
Summary: Escaneo y análisis de textos en cadenas o ficheros. Scanning and analyzing texts in strings or files.
Author: miloter
License-Expression: MIT
Project-URL: Repository, https://github.com/miloter/scannertext
Keywords: analizador,sintáctico,sintax,analyze
Classifier: Operating System :: OS Independent
Classifier: Programming Language :: Python :: 3.6
Requires-Python: >=3.6
License-File: LICENSE
Dynamic: license-file
